nitro_ui/__init__.py
nitro_ui/core/__init__.py
nitro_ui/core/component.py
nitro_ui/core/element.py
nitro_ui/core/factory.py
nitro_ui/core/fragment.py
nitro_ui/core/parser.py
nitro_ui/core/partial.py
nitro_ui/core/slot.py
nitro_ui/forms/__init__.py
nitro_ui/forms/field.py
nitro_ui/styles/__init__.py
nitro_ui/styles/style.py
nitro_ui/styles/stylesheet.py
nitro_ui/styles/theme.py
nitro_ui/tags/__init__.py
nitro_ui/tags/form.py
nitro_ui/tags/html.py
nitro_ui/tags/layout.py
nitro_ui/tags/lists.py
nitro_ui/tags/media.py
nitro_ui/tags/table.py
nitro_ui/tags/tag_factory.py
nitro_ui/tags/text.py
nitro_ui-1.0.7.dist-info/licenses/LICENSE
nitro_ui-1.0.7.dist-info/METADATA
nitro_ui-1.0.7.dist-info/WHEEL
nitro_ui-1.0.7.dist-info/top_level.txt
nitro_ui-1.0.7.dist-info/RECORD
