Metadata-Version: 2.4
Name: nitro-ui
Version: 1.0.7
Summary: Build HTML with Python, not strings. Zero-dependency library with type-safe elements, method chaining, and JSON serialization.
Author-email: Sean Nieuwoudt <sean@underwulf.com>
Project-URL: Homepage, https://github.com/nitro-sh/nitro-ui
Project-URL: Documentation, https://github.com/nitro-sh/nitro-ui#readme
Project-URL: Repository, https://github.com/nitro-sh/nitro-ui
Project-URL: Issues, https://github.com/nitro-sh/nitro-ui/issues
Keywords: json,ui,framework,html,components,frontend
Classifier: Operating System :: OS Independent
Classifier: Development Status :: 5 - Production/Stable
Classifier: Intended Audience :: Developers
Classifier: License :: OSI Approved :: BSD License
Classifier: Programming Language :: Python :: 3
Classifier: Programming Language :: Python :: 3.8
Classifier: Programming Language :: Python :: 3.9
Classifier: Programming Language :: Python :: 3.10
Classifier: Programming Language :: Python :: 3.11
Classifier: Programming Language :: Python :: 3.12
Classifier: Programming Language :: Python :: 3.13
Classifier: Programming Language :: Python :: 3.14
Classifier: Topic :: Software Development :: Libraries :: Python Modules
Classifier: Topic :: Utilities
Classifier: Natural Language :: English
Requires-Python: >=3.8
License-File: LICENSE
Provides-Extra: dev
Requires-Dist: pytest>=7.0; extra == "dev"
Requires-Dist: pytest-cov>=4.0; extra == "dev"
Requires-Dist: black>=24.0; extra == "dev"
Requires-Dist: flake8>=7.0; extra == "dev"
Dynamic: license-file
